CHANGES.txt
MANIFEST.in
README.md
setup.py
chronicle/__init__.py
chronicle/gunicorn.py
chronicle.egg-info/PKG-INFO
chronicle.egg-info/SOURCES.txt
chronicle.egg-info/dependency_links.txt
chronicle.egg-info/not-zip-safe
chronicle.egg-info/requires.txt
chronicle.egg-info/top_level.txt
chronicle/flask/__init__.py
chronicle/flask/wag.py
chronicle/pyramid/__init__.py
chronicle/sentry/__init__.py
chronicle/sentry/flask.py
chronicle/sentry/pyramid.py