Metadata-Version: 1.1
Name: chronicle
Version: 1.0.7
Summary: logging utils
Home-page: UNKNOWN
Author: Balanced
Author-email: dev+bob@balancedpayments.com
License: UNKNOWN
Platform: UNKNOWN
Classifier: Programming Language :: Python
